LICENSE
ez_task/__init__.py
ez_task/config/__init__.py
ez_task/config/config.py
ez_task/gatherer/__init__.py
ez_task/gatherer/gatherer.py
ez_task/manager.py
ez_task/task.py
ez_task/types/__init__.py
ez_task/types/exceptions/__init__.py
ez_task/types/exceptions/task.py
ez_task/types/health_check.py
ez_task-0.1.2.dist-info/LICENSE
ez_task-0.1.2.dist-info/WHEEL
ez_task-0.1.2.dist-info/METADATA
ez_task-0.1.2.dist-info/RECORD
