Metadata-Version: 2.1
Name: ez-task
Version: 0.1.2
Summary: A small package for simple multiprocessing
License: MIT
Keywords: multiprocessing,tasks
Author: Chris Moyer
Author-email: chris@telemetry.fm
Requires-Python: >=3.7
Classifier: Environment :: Console
Classifier: License :: OSI Approved :: MIT License
Classifier: Operating System :: OS Independent
Classifier: Programming Language :: Python :: 3
Classifier: Programming Language :: Python :: 3.7
Classifier: Programming Language :: Python :: 3.8
Classifier: Programming Language :: Python :: 3.9
Classifier: Programming Language :: Python :: 3.10
Classifier: Programming Language :: Python :: 3.11
